fogbugz.py
fogbugz_bis-1.2.0.dist-info/LICENSE
fogbugz_bis-1.2.0.dist-info/METADATA
fogbugz_bis-1.2.0.dist-info/WHEEL
fogbugz_bis-1.2.0.dist-info/top_level.txt
fogbugz_bis-1.2.0.dist-info/RECORD
