Metadata-Version: 2.1
Name: fogbugz-bis
Version: 1.2.0
Summary: Python library for interacting with the FogBugz API
Home-page: https://github.com/yougov/FogBugzPy
Author: Fog Creek Software
Author-email: customer-service@fogcreek.com
Maintainer: YouGov, Plc.
Maintainer-email: open-source@yougov.com
Classifier: Development Status :: 5 - Production/Stable
Classifier: Intended Audience :: Developers
Classifier: License :: OSI Approved :: MIT License
Classifier: Programming Language :: Python :: 3
Classifier: Programming Language :: Python :: 3 :: Only
Classifier: Natural Language :: English
Classifier: Operating System :: MacOS :: MacOS X
Classifier: Operating System :: Microsoft :: Windows
Classifier: Operating System :: POSIX
Classifier: Operating System :: POSIX :: BSD
Classifier: Operating System :: POSIX :: Linux
Classifier: Topic :: Internet :: WWW/HTTP
Classifier: Topic :: Software Development
Classifier: Topic :: Software Development :: Bug Tracking
Classifier: Topic :: Software Development :: Libraries
Classifier: Topic :: Software Development :: Libraries :: Python Modules
Classifier: Topic :: Software Development :: Version Control
Classifier: Topic :: Utilities
Requires-Python: >=3.7
License-File: LICENSE
Requires-Dist: BeautifulSoup4
Requires-Dist: lxml
Requires-Dist: six
Provides-Extra: docs
Requires-Dist: sphinx ; extra == 'docs'
Requires-Dist: jaraco.packaging (>=9) ; extra == 'docs'
Requires-Dist: rst.linker (>=1.9) ; extra == 'docs'
Provides-Extra: testing
Requires-Dist: pytest (>=6) ; extra == 'testing'
Requires-Dist: pytest-checkdocs (>=2.4) ; extra == 'testing'
Requires-Dist: pytest-flake8 ; extra == 'testing'
Requires-Dist: flake8 (<5) ; extra == 'testing'
Requires-Dist: pytest-cov ; extra == 'testing'
Requires-Dist: pytest-enabler (>=1.3) ; extra == 'testing'
Requires-Dist: pytest-black (>=0.3.7) ; (platform_python_implementation != "PyPy") and extra == 'testing'
Requires-Dist: pytest-mypy (>=0.9.1) ; (platform_python_implementation != "PyPy") and extra == 'testing'
